lab317/__init__.py
lab317/timeoutprocess.py
lab317/utils.py
lab317-0.0.4.dist-info/METADATA
lab317-0.0.4.dist-info/WHEEL
lab317-0.0.4.dist-info/top_level.txt
lab317-0.0.4.dist-info/RECORD
