Metadata-Version: 2.1
Name: lab317
Version: 0.0.4
Summary: Utils for sparta lab - hussam
Home-page: UNKNOWN
Author: Hussam Habib
Author-email: hussam-habib@uiowa.edu
License: UNKNOWN
Keywords: utilities
Platform: UNKNOWN
Classifier: Development Status :: 1 - Planning
Classifier: Intended Audience :: Developers
Classifier: Programming Language :: Python :: 3
Classifier: Operating System :: Unix
Classifier: Operating System :: MacOS :: MacOS X
Classifier: Operating System :: Microsoft :: Windows
Requires-Dist: datetime
